[ {"Id": 52569, "VIN": "2T1BU4EE9BC584898", "Model": "RENAULT DUSTER", "DeviceId": 375308, "RegNumber": "C 853 MY 151", "ReleaseDate": null, "InventoryNumber": ""},
  {"Id": 52570, "VIN": "5J8TB1H56BA020250", "Model": "KIA CEED", "DeviceId": 375297, "RegNumber": "B 472 PB 643", "ReleaseDate": null, "InventoryNumber": ""},
  {"Id": 52571, "VIN": "4M2ZU86K05UJ26128", "Model": "RENAULT DUSTER", "DeviceId": 375302, "RegNumber": "B 953 AK 265", "ReleaseDate": null, "InventoryNumber": ""},
  {"Id": 52572, "VIN": "WMWRC33465TC72136", "Model": "Kia Ceed", "DeviceId": 375309, "RegNumber": "P 196 EO 488", "ReleaseDate": null, "InventoryNumber": ""},
  {"Id": 52573, "VIN": "1MEFM50U1XA696868", "Model": "FORD FOCUS", "DeviceId": 375310, "RegNumber": "A 564 AA 335", "ReleaseDate": null, "InventoryNumber": null},
  {"Id": 52574, "VIN": "1G1125S33EU129894", "Model": "Renault Logan", "DeviceId": 375060, "RegNumber": "K 935 OP 686", "ReleaseDate": null, "InventoryNumber": null},
  {"Id": 52575, "VIN": "2C3KA53G17H709462", "Model": "Renault Logan", "DeviceId": 375194, "RegNumber": "K 594 TB 127", "ReleaseDate": null, "InventoryNumber": ""},
  {"Id": 52576, "VIN": "4T1BK1EBXEU158103", "Model": "Renault Logan", "DeviceId": 375184, "RegNumber": "T 174 AY 579", "ReleaseDate": null, "InventoryNumber": "072599"},
  {"Id": 52577, "VIN": "1FDLE40S0VHA63692", "Model": "Skoda SUPERB", "DeviceId": 375311, "RegNumber": "M 848 TM 238", "ReleaseDate": null, "InventoryNumber": ""},
  {"Id": 52578, "VIN": "1G2ZH57N984173376", "Model": "Volkswagen Passat", "DeviceId": 375307, "RegNumber": "M 219 HB 537", "ReleaseDate": null, "InventoryNumber": "035490"},
  {"Id": 52579, "VIN": "2HNYD28358H547039", "Model": "TOYO TG-28TPC", "DeviceId": 375106, "RegNumber": "A 788 OM 148", "ReleaseDate": null, "InventoryNumber": "132"},
  {"Id": 52580, "VIN": "KNAFT4A20C5573204", "Model": "Airman PDS 100 S", "DeviceId": 375119, "RegNumber": "C 428 PY 621", "ReleaseDate": null, "InventoryNumber": "142"},
  {"Id": 52581, "VIN": "5XYKT4A6XFG682141", "Model": "STEW, FT-2251", "DeviceId": null, "RegNumber": "Y 552 AX 428", "ReleaseDate": null, "InventoryNumber": "ГРП"},
  {"Id": 70583, "VIN": null, "Model": null, "DeviceId": 5136324, "RegNumber": "Х 456 ХХ 444", "ReleaseDate": null, "InventoryNumber": null},
  {"Id": 75915, "VIN": null, "Model": "Камаз МКД-4705", "DeviceId": 5142135, "RegNumber": "В 186 АХ 576", "ReleaseDate": null, "InventoryNumber": null},
  {"Id": 75916, "VIN": null, "Model": "МТЗ-82", "DeviceId": 5142136, "RegNumber": "6709 ХВ 88", "ReleaseDate": null, "InventoryNumber": "283"},
  {"Id": 75917, "VIN": null, "Model": "КАМАЗ МКДС 4705", "DeviceId": 5142137, "RegNumber": "Х 412 КЕ 971", "ReleaseDate": null, "InventoryNumber": "99"},
  {"Id": 75918, "VIN": null, "Model": "МТЗ 82.МК-РТР-1 на шасси БЕЛАРУС 82", "DeviceId": 5142138, "RegNumber": "4449 ТУ 619", "ReleaseDate": null, "InventoryNumber": "431"},
  {"Id": 75919, "VIN": null, "Model": "БЕЛАРУС 82", "DeviceId": 5142139, "RegNumber": "7054 АР 714", "ReleaseDate": null, "InventoryNumber": null},
  {"Id": 75922, "VIN": null, "Model": "МКДС 4705 на шасси КАМАЗ 65115-62", "DeviceId": 5142140, "RegNumber": "К 862 НР 88", "ReleaseDate": null, "InventoryNumber": null},
  {"Id": 75925, "VIN": null, "Model": "МТЗ 82.МК-РТР-1 на шасси БЕЛАРУС 82", "DeviceId": 5142141, "RegNumber": "1905 РО 691", "ReleaseDate": null, "InventoryNumber": null},
  {"Id": 75926, "VIN": null, "Model": "МППУ-1", "DeviceId": 5142142, "RegNumber": "8793 КН 412", "ReleaseDate": null, "InventoryNumber": null},
  {"Id": 75927, "VIN": null, "Model": "КАМАЗ 65115-82", "DeviceId": 5142143, "RegNumber": "Р 491 УТ 599", "ReleaseDate": null, "InventoryNumber": null},
  {"Id": 75928, "VIN": null, "Model": "КАМАЗ", "DeviceId": 5142144, "RegNumber": "Р 914 НЕ 286", "ReleaseDate": null, "InventoryNumber": null},
  {"Id": 76237, "VIN": null, "Model": "6890В КАМАЗ", "DeviceId": 5142287, "RegNumber": "Т 918 АС 961", "ReleaseDate": null, "InventoryNumber": null},
  {"Id": 76238, "VIN": null, "Model": "ГАЗель Чайка-Сервис 27840P", "DeviceId": 5142288, "RegNumber": "Н 098 АК 288", "ReleaseDate": null, "InventoryNumber": null},
  {"Id": 76241, "VIN": null, "Model": "ГАЗ АП-18-07", "DeviceId": 5142289, "RegNumber": "Р 713 ОЕ 417", "ReleaseDate": null, "InventoryNumber": null},
  {"Id": 76242, "VIN": null, "Model": "КамАЗ-58492Р", "DeviceId": 5142290, "RegNumber": "У 381 ТЕ 653", "ReleaseDate": null, "InventoryNumber": null},
  {"Id": 76243, "VIN": null, "Model": "ВМК-10 КАМАЗ-43253", "DeviceId": 5142291, "RegNumber": "Е 819 НР 312", "ReleaseDate": null, "InventoryNumber": null},
  {"Id": 76250, "VIN": null, "Model": "MAN TGM 19.250", "DeviceId": 5142292, "RegNumber": "Р 768 ОУ 481", "ReleaseDate": null, "InventoryNumber": null},
  {"Id": 76252, "VIN": null, "Model": "КАМАЗ Bucher CityFant 6000", "DeviceId": 5142293, "RegNumber": "Х 594 ХС 072", "ReleaseDate": null, "InventoryNumber": null},
  {"Id": 76253, "VIN": null, "Model": "Samangan СHD5167CQX4", "DeviceId": 5142294, "RegNumber": "М 091 ОР 593", "ReleaseDate": null, "InventoryNumber": null},
  {"Id": 76255, "VIN": null, "Model": "LiuGong 4215D", "DeviceId": 5142295, "RegNumber": "Е 891 ОН 436", "ReleaseDate": null, "InventoryNumber": null}
]
